artdep-0.2.4.dist-info/licenses/LICENSE
matmacore/__init__.py
matmacore/mol.py
matmacore/plot.py
matmacore/utilities.py
artdep-0.2.4.dist-info/METADATA
artdep-0.2.4.dist-info/WHEEL
artdep-0.2.4.dist-info/top_level.txt
artdep-0.2.4.dist-info/RECORD
