Metadata-Version: 2.4
Name: artdep
Version: 0.2.4
Summary: Add your description here
Requires-Python: >=3.12
License-File: LICENSE
Dynamic: license-file
